{
  "info": {
    "description": "Wheat head counting dataset",
    "version": "1.0",
    "year": 2025,
    "contributor": "Agricultural AI",
    "source": "augmented",
    "license": {
      "name": "Creative Commons Attribution 4.0 International",
      "url": "https://creativecommons.org/licenses/by/4.0/"
    }
  },
  "images": [
    {
      "id": 9007485165,
      "width": 1024,
      "height": 1024,
      "file_name": "d1f17b45afeb8645d4dcb0acde7407790caeccd1f5a0ce3587b97b3979301efa.png",
      "size": 2374475,
      "format": "PNG",
      "url": "",
      "hash": "",
      "status": "success"
    }
  ],
  "annotations": [
    {
      "id": 3976552165,
      "image_id": 9007485165,
      "category_id": 1,
      "segmentation": [],
      "area": 16320,
      "bbox": [
        39,
        854,
        96,
        170
      ]
    },
    {
      "id": 3976552166,
      "image_id": 9007485165,
      "category_id": 1,
      "segmentation": [],
      "area": 5589,
      "bbox": [
        222,
        659,
        69,
        81
      ]
    },
    {
      "id": 3976552167,
      "image_id": 9007485165,
      "category_id": 1,
      "segmentation": [],
      "area": 7830,
      "bbox": [
        415,
        748,
        90,
        87
      ]
    },
    {
      "id": 3976552168,
      "image_id": 9007485165,
      "category_id": 1,
      "segmentation": [],
      "area": 3564,
      "bbox": [
        435,
        980,
        81,
        44
      ]
    },
    {
      "id": 3976552169,
      "image_id": 9007485165,
      "category_id": 1,
      "segmentation": [],
      "area": 5695,
      "bbox": [
        748,
        65,
        85,
        67
      ]
    },
    {
      "id": 3976552170,
      "image_id": 9007485165,
      "category_id": 1,
      "segmentation": [],
      "area": 5609,
      "bbox": [
        633,
        167,
        79,
        71
      ]
    },
    {
      "id": 3976552171,
      "image_id": 9007485165,
      "category_id": 1,
      "segmentation": [],
      "area": 10010,
      "bbox": [
        500,
        933,
        110,
        91
      ]
    },
    {
      "id": 3976552172,
      "image_id": 9007485165,
      "category_id": 1,
      "segmentation": [],
      "area": 13832,
      "bbox": [
        521,
        25,
        152,
        91
      ]
    },
    {
      "id": 3976552173,
      "image_id": 9007485165,
      "category_id": 1,
      "segmentation": [],
      "area": 6441,
      "bbox": [
        893,
        0,
        113,
        57
      ]
    },
    {
      "id": 3976552174,
      "image_id": 9007485165,
      "category_id": 1,
      "segmentation": [],
      "area": 11172,
      "bbox": [
        230,
        884,
        84,
        133
      ]
    },
    {
      "id": 3976552175,
      "image_id": 9007485165,
      "category_id": 1,
      "segmentation": [],
      "area": 6380,
      "bbox": [
        171,
        0,
        116,
        55
      ]
    },
    {
      "id": 3976552176,
      "image_id": 9007485165,
      "category_id": 1,
      "segmentation": [],
      "area": 16224,
      "bbox": [
        628,
        393,
        104,
        156
      ]
    },
    {
      "id": 3976552177,
      "image_id": 9007485165,
      "category_id": 1,
      "segmentation": [],
      "area": 4539,
      "bbox": [
        685,
        6,
        89,
        51
      ]
    },
    {
      "id": 3976552178,
      "image_id": 9007485165,
      "category_id": 1,
      "segmentation": [],
      "area": 15600,
      "bbox": [
        0,
        651,
        104,
        150
      ]
    },
    {
      "id": 3976552179,
      "image_id": 9007485165,
      "category_id": 1,
      "segmentation": [],
      "area": 17664,
      "bbox": [
        144,
        828,
        128,
        138
      ]
    },
    {
      "id": 3976552180,
      "image_id": 9007485165,
      "category_id": 1,
      "segmentation": [],
      "area": 5762,
      "bbox": [
        744,
        742,
        67,
        86
      ]
    },
    {
      "id": 3976552181,
      "image_id": 9007485165,
      "category_id": 1,
      "segmentation": [],
      "area": 5538,
      "bbox": [
        289,
        57,
        71,
        78
      ]
    },
    {
      "id": 3976552182,
      "image_id": 9007485165,
      "category_id": 1,
      "segmentation": [],
      "area": 15372,
      "bbox": [
        555,
        898,
        122,
        126
      ]
    },
    {
      "id": 3976552183,
      "image_id": 9007485165,
      "category_id": 1,
      "segmentation": [],
      "area": 3243,
      "bbox": [
        952,
        955,
        47,
        69
      ]
    },
    {
      "id": 3976552184,
      "image_id": 9007485165,
      "category_id": 1,
      "segmentation": [],
      "area": 8645,
      "bbox": [
        842,
        933,
        95,
        91
      ]
    },
    {
      "id": 3976552185,
      "image_id": 9007485165,
      "category_id": 1,
      "segmentation": [],
      "area": 10208,
      "bbox": [
        535,
        368,
        116,
        88
      ]
    },
    {
      "id": 3976552186,
      "image_id": 9007485165,
      "category_id": 1,
      "segmentation": [],
      "area": 8370,
      "bbox": [
        403,
        565,
        93,
        90
      ]
    },
    {
      "id": 3976552187,
      "image_id": 9007485165,
      "category_id": 1,
      "segmentation": [],
      "area": 7704,
      "bbox": [
        819,
        206,
        72,
        107
      ]
    },
    {
      "id": 3976552188,
      "image_id": 9007485165,
      "category_id": 1,
      "segmentation": [],
      "area": 8004,
      "bbox": [
        135,
        736,
        87,
        92
      ]
    },
    {
      "id": 3976552189,
      "image_id": 9007485165,
      "category_id": 1,
      "segmentation": [],
      "area": 8400,
      "bbox": [
        537,
        577,
        105,
        80
      ]
    },
    {
      "id": 3976552190,
      "image_id": 9007485165,
      "category_id": 1,
      "segmentation": [],
      "area": 10192,
      "bbox": [
        805,
        507,
        112,
        91
      ]
    },
    {
      "id": 3976552191,
      "image_id": 9007485165,
      "category_id": 1,
      "segmentation": [],
      "area": 6160,
      "bbox": [
        748,
        417,
        80,
        77
      ]
    },
    {
      "id": 3976552192,
      "image_id": 9007485165,
      "category_id": 1,
      "segmentation": [],
      "area": 8502,
      "bbox": [
        185,
        190,
        78,
        109
      ]
    },
    {
      "id": 3976552193,
      "image_id": 9007485165,
      "category_id": 1,
      "segmentation": [],
      "area": 9612,
      "bbox": [
        842,
        799,
        89,
        108
      ]
    },
    {
      "id": 3976552194,
      "image_id": 9007485165,
      "category_id": 1,
      "segmentation": [],
      "area": 6970,
      "bbox": [
        118,
        543,
        82,
        85
      ]
    },
    {
      "id": 3976552195,
      "image_id": 9007485165,
      "category_id": 1,
      "segmentation": [],
      "area": 2457,
      "bbox": [
        0,
        876,
        39,
        63
      ]
    },
    {
      "id": 3976552196,
      "image_id": 9007485165,
      "category_id": 1,
      "segmentation": [],
      "area": 5395,
      "bbox": [
        0,
        153,
        65,
        83
      ]
    },
    {
      "id": 3976552197,
      "image_id": 9007485165,
      "category_id": 1,
      "segmentation": [],
      "area": 6205,
      "bbox": [
        415,
        72,
        85,
        73
      ]
    }
  ],
  "categories": [
    {
      "id": 1,
      "name": "wheat_head",
      "supercategory": "broccoli"
    }
  ]
}