{
  "info": {
    "description": "Wheat head counting dataset",
    "version": "1.0",
    "year": 2025,
    "contributor": "Agricultural AI",
    "source": "augmented",
    "license": {
      "name": "Creative Commons Attribution 4.0 International",
      "url": "https://creativecommons.org/licenses/by/4.0/"
    }
  },
  "images": [
    {
      "id": 3547081168,
      "width": 1024,
      "height": 1024,
      "file_name": "dfd84e526f885b23a5c19cd03ca8145cb94da2aa03571d9bbcde5a84e2f70db6.png",
      "size": 2368286,
      "format": "PNG",
      "url": "",
      "hash": "",
      "status": "success"
    }
  ],
  "annotations": [
    {
      "id": 9495221168,
      "image_id": 3547081168,
      "category_id": 1,
      "segmentation": [],
      "area": 6318,
      "bbox": [
        114,
        807,
        81,
        78
      ]
    },
    {
      "id": 9495221169,
      "image_id": 3547081168,
      "category_id": 1,
      "segmentation": [],
      "area": 8262,
      "bbox": [
        669,
        73,
        102,
        81
      ]
    },
    {
      "id": 9495221170,
      "image_id": 3547081168,
      "category_id": 1,
      "segmentation": [],
      "area": 7007,
      "bbox": [
        499,
        487,
        77,
        91
      ]
    },
    {
      "id": 9495221171,
      "image_id": 3547081168,
      "category_id": 1,
      "segmentation": [],
      "area": 11004,
      "bbox": [
        717,
        937,
        131,
        84
      ]
    },
    {
      "id": 9495221172,
      "image_id": 3547081168,
      "category_id": 1,
      "segmentation": [],
      "area": 5950,
      "bbox": [
        3,
        102,
        85,
        70
      ]
    },
    {
      "id": 9495221173,
      "image_id": 3547081168,
      "category_id": 1,
      "segmentation": [],
      "area": 3960,
      "bbox": [
        570,
        0,
        66,
        60
      ]
    },
    {
      "id": 9495221174,
      "image_id": 3547081168,
      "category_id": 1,
      "segmentation": [],
      "area": 2756,
      "bbox": [
        0,
        0,
        53,
        52
      ]
    },
    {
      "id": 9495221175,
      "image_id": 3547081168,
      "category_id": 1,
      "segmentation": [],
      "area": 14691,
      "bbox": [
        107,
        168,
        177,
        83
      ]
    },
    {
      "id": 9495221176,
      "image_id": 3547081168,
      "category_id": 1,
      "segmentation": [],
      "area": 4930,
      "bbox": [
        491,
        32,
        85,
        58
      ]
    },
    {
      "id": 9495221177,
      "image_id": 3547081168,
      "category_id": 1,
      "segmentation": [],
      "area": 12744,
      "bbox": [
        361,
        652,
        118,
        108
      ]
    },
    {
      "id": 9495221178,
      "image_id": 3547081168,
      "category_id": 1,
      "segmentation": [],
      "area": 18396,
      "bbox": [
        893,
        364,
        126,
        146
      ]
    },
    {
      "id": 9495221179,
      "image_id": 3547081168,
      "category_id": 1,
      "segmentation": [],
      "area": 4760,
      "bbox": [
        592,
        670,
        70,
        68
      ]
    },
    {
      "id": 9495221180,
      "image_id": 3547081168,
      "category_id": 1,
      "segmentation": [],
      "area": 2695,
      "bbox": [
        0,
        123,
        35,
        77
      ]
    },
    {
      "id": 9495221181,
      "image_id": 3547081168,
      "category_id": 1,
      "segmentation": [],
      "area": 8784,
      "bbox": [
        549,
        946,
        122,
        72
      ]
    },
    {
      "id": 9495221182,
      "image_id": 3547081168,
      "category_id": 1,
      "segmentation": [],
      "area": 8881,
      "bbox": [
        80,
        376,
        83,
        107
      ]
    },
    {
      "id": 9495221183,
      "image_id": 3547081168,
      "category_id": 1,
      "segmentation": [],
      "area": 11562,
      "bbox": [
        596,
        455,
        82,
        141
      ]
    },
    {
      "id": 9495221184,
      "image_id": 3547081168,
      "category_id": 1,
      "segmentation": [],
      "area": 7656,
      "bbox": [
        808,
        76,
        88,
        87
      ]
    },
    {
      "id": 9495221185,
      "image_id": 3547081168,
      "category_id": 1,
      "segmentation": [],
      "area": 18340,
      "bbox": [
        183,
        404,
        131,
        140
      ]
    },
    {
      "id": 9495221186,
      "image_id": 3547081168,
      "category_id": 1,
      "segmentation": [],
      "area": 5135,
      "bbox": [
        271,
        62,
        65,
        79
      ]
    },
    {
      "id": 9495221187,
      "image_id": 3547081168,
      "category_id": 1,
      "segmentation": [],
      "area": 11284,
      "bbox": [
        331,
        1,
        91,
        124
      ]
    },
    {
      "id": 9495221188,
      "image_id": 3547081168,
      "category_id": 1,
      "segmentation": [],
      "area": 2210,
      "bbox": [
        143,
        997,
        85,
        26
      ]
    },
    {
      "id": 9495221189,
      "image_id": 3547081168,
      "category_id": 1,
      "segmentation": [],
      "area": 5148,
      "bbox": [
        958,
        687,
        66,
        78
      ]
    },
    {
      "id": 9495221190,
      "image_id": 3547081168,
      "category_id": 1,
      "segmentation": [],
      "area": 3417,
      "bbox": [
        634,
        1,
        67,
        51
      ]
    },
    {
      "id": 9495221191,
      "image_id": 3547081168,
      "category_id": 1,
      "segmentation": [],
      "area": 7380,
      "bbox": [
        0,
        657,
        90,
        82
      ]
    },
    {
      "id": 9495221192,
      "image_id": 3547081168,
      "category_id": 1,
      "segmentation": [],
      "area": 6561,
      "bbox": [
        943,
        240,
        81,
        81
      ]
    },
    {
      "id": 9495221193,
      "image_id": 3547081168,
      "category_id": 1,
      "segmentation": [],
      "area": 13900,
      "bbox": [
        368,
        295,
        100,
        139
      ]
    },
    {
      "id": 9495221194,
      "image_id": 3547081168,
      "category_id": 1,
      "segmentation": [],
      "area": 4648,
      "bbox": [
        393,
        885,
        83,
        56
      ]
    },
    {
      "id": 9495221195,
      "image_id": 3547081168,
      "category_id": 1,
      "segmentation": [],
      "area": 8103,
      "bbox": [
        864,
        419,
        73,
        111
      ]
    },
    {
      "id": 9495221196,
      "image_id": 3547081168,
      "category_id": 1,
      "segmentation": [],
      "area": 10880,
      "bbox": [
        183,
        841,
        128,
        85
      ]
    },
    {
      "id": 9495221197,
      "image_id": 3547081168,
      "category_id": 1,
      "segmentation": [],
      "area": 7169,
      "bbox": [
        671,
        187,
        107,
        67
      ]
    },
    {
      "id": 9495221198,
      "image_id": 3547081168,
      "category_id": 1,
      "segmentation": [],
      "area": 9309,
      "bbox": [
        159,
        54,
        107,
        87
      ]
    }
  ],
  "categories": [
    {
      "id": 1,
      "name": "wheat_head",
      "supercategory": "broccoli"
    }
  ]
}